{"0.19": {"n_systems": 37, "files": {"A": "/home/user/code/relevance_prediction/output/ranking_performance/ranking_performance.nist.dl19-passage.json", "B": "/home/user/code/relevance_prediction/output/ranking_performance/ranking_performance.rank1-7b.dl19-passage/0.19.json"}, "metrics": {"ndcg@10": {"kendall_tau": 0.8648648648648649, "kendall_tau_p": 4.942240688409104e-14, "spearman_rho": 0.9642010431484115, "spearman_rho_p": 9.23078457180987e-22}, "map@100": {"kendall_tau": 0.897897897897898, "kendall_tau_p": 5.233421599100931e-15, "spearman_rho": 0.9791370317686106, "spearman_rho_p": 8.182123953070416e-26}, "mrr@10": {"kendall_tau": 0.8316983500743235, "kendall_tau_p": 5.563603535575372e-13, "spearman_rho": 0.9517343627759418, "spearman_rho_p": 1.5599261236667657e-19}}}, "0.52": {"n_systems": 37, "files": {"A": "/home/user/code/relevance_prediction/output/ranking_performance/ranking_performance.nist.dl19-passage.json", "B": "/home/user/code/relevance_prediction/output/ranking_performance/ranking_performance.rank1-7b.dl19-passage/0.52.json"}, "metrics": {"ndcg@10": {"kendall_tau": 0.8528528528528528, "kendall_tau_p": 1.0958355703875995e-13, "spearman_rho": 0.9615931721194878, "spearman_rho_p": 3.095035855301447e-21}, "map@100": {"kendall_tau": 0.897897897897898, "kendall_tau_p": 5.233421599100931e-15, "spearman_rho": 0.9803224276908485, "spearman_rho_p": 2.9671574948533413e-26}, "mrr@10": {"kendall_tau": 0.8347172188586224, "kendall_tau_p": 4.589068655265418e-13, "spearman_rho": 0.9524458955373467, "spearman_rho_p": 1.209743137794585e-19}}}, "0.63": {"n_systems": 37, "files": {"A": "/home/user/code/relevance_prediction/output/ranking_performance/ranking_performance.nist.dl19-passage.json", "B": "/home/user/code/relevance_prediction/output/ranking_performance/ranking_performance.rank1-7b.dl19-passage/0.63.json"}, "metrics": {"ndcg@10": {"kendall_tau": 0.8558558558558559, "kendall_tau_p": 8.989354747556581e-14, "spearman_rho": 0.9623044096728307, "spearman_rho_p": 2.2441673781450668e-21}, "map@100": {"kendall_tau": 0.9009009009009009, "kendall_tau_p": 4.249922767583786e-15, "spearman_rho": 0.980796586059744, "spearman_rho_p": 1.943493430675664e-26}, "mrr@10": {"kendall_tau": 0.8347172188586224, "kendall_tau_p": 4.589068655265418e-13, "spearman_rho": 0.9524458955373467, "spearman_rho_p": 1.209743137794585e-19}}}, "0.28": {"n_systems": 37, "files": {"A": "/home/user/code/relevance_prediction/output/ranking_performance/ranking_performance.nist.dl19-passage.json", "B": "/home/user/code/relevance_prediction/output/ranking_performance/ranking_performance.rank1-7b.dl19-passage/0.28.json"}, "metrics": {"ndcg@10": {"kendall_tau": 0.8618618618618619, "kendall_tau_p": 6.036953062344684e-14, "spearman_rho": 0.9642010431484115, "spearman_rho_p": 9.23078457180987e-22}, "map@100": {"kendall_tau": 0.897897897897898, "kendall_tau_p": 5.233421599100931e-15, "spearman_rho": 0.9796111901375059, "spearman_rho_p": 5.492427427607869e-26}, "mrr@10": {"kendall_tau": 0.8347172188586224, "kendall_tau_p": 4.589068655265418e-13, "spearman_rho": 0.9524458955373467, "spearman_rho_p": 1.209743137794585e-19}}}, "0.01": {"n_systems": 37, "files": {"A": "/home/user/code/relevance_prediction/output/ranking_performance/ranking_performance.nist.dl19-passage.json", "B": "/home/user/code/relevance_prediction/output/ranking_performance/ranking_performance.rank1-7b.dl19-passage/0.01.json"}, "metrics": {"ndcg@10": {"kendall_tau": 0.882882882882883, "kendall_tau_p": 1.4669621265310082e-14, "spearman_rho": 0.9746325272641062, "spearman_rho_p": 2.416615782010569e-24}, "map@100": {"kendall_tau": 0.8918918918918919, "kendall_tau_p": 7.919850073206233e-15, "spearman_rho": 0.9774774774774774, "spearman_rho_p": 3.0824933035727987e-25}, "mrr@10": {"kendall_tau": 0.8467926939958176, "kendall_tau_p": 2.109957915705253e-13, "spearman_rho": 0.9576045080575328, "spearman_rho_p": 1.6898299755388276e-20}}}, "0.92": {"n_systems": 37, "files": {"A": "/home/user/code/relevance_prediction/output/ranking_performance/ranking_performance.nist.dl19-passage.json", "B": "/home/user/code/relevance_prediction/output/ranking_performance/ranking_performance.rank1-7b.dl19-passage/0.92.json"}, "metrics": {"ndcg@10": {"kendall_tau": 0.8498498498498499, "kendall_tau_p": 1.3349653228005416e-13, "spearman_rho": 0.9611190137505926, "spearman_rho_p": 3.8219476497508666e-21}, "map@100": {"kendall_tau": 0.9009009009009009, "kendall_tau_p": 4.249922767583786e-15, "spearman_rho": 0.9803224276908485, "spearman_rho_p": 2.9671574948533413e-26}, "mrr@10": {"kendall_tau": 0.8347172188586224, "kendall_tau_p": 4.589068655265418e-13, "spearman_rho": 0.9524458955373467, "spearman_rho_p": 1.209743137794585e-19}}}, "0.67": {"n_systems": 37, "files": {"A": "/home/user/code/relevance_prediction/output/ranking_performance/ranking_performance.nist.dl19-passage.json", "B": "/home/user/code/relevance_prediction/output/ranking_performance/ranking_performance.rank1-7b.dl19-passage/0.67.json"}, "metrics": {"ndcg@10": {"kendall_tau": 0.8558558558558559, "kendall_tau_p": 8.989354747556581e-14, "spearman_rho": 0.9623044096728307, "spearman_rho_p": 2.2441673781450668e-21}, "map@100": {"kendall_tau": 0.9009009009009009, "kendall_tau_p": 4.249922767583786e-15, "spearman_rho": 0.980796586059744, "spearman_rho_p": 1.943493430675664e-26}, "mrr@10": {"kendall_tau": 0.8347172188586224, "kendall_tau_p": 4.589068655265418e-13, "spearman_rho": 0.9524458955373467, "spearman_rho_p": 1.209743137794585e-19}}}, "0.56": {"n_systems": 37, "files": {"A": "/home/user/code/relevance_prediction/output/ranking_performance/ranking_performance.nist.dl19-passage.json", "B": "/home/user/code/relevance_prediction/output/ranking_performance/ranking_performance.rank1-7b.dl19-passage/0.56.json"}, "metrics": {"ndcg@10": {"kendall_tau": 0.8468468468468467, "kendall_tau_p": 1.625183200282792e-13, "spearman_rho": 0.9601706970128023, "spearman_rho_p": 5.783059808490516e-21}, "map@100": {"kendall_tau": 0.897897897897898, "kendall_tau_p": 5.233421599100931e-15, "spearman_rho": 0.9803224276908485, "spearman_rho_p": 2.9671574948533413e-26}, "mrr@10": {"kendall_tau": 0.8347172188586224, "kendall_tau_p": 4.589068655265418e-13, "spearman_rho": 0.9524458955373467, "spearman_rho_p": 1.209743137794585e-19}}}, "0.96": {"n_systems": 37, "files": {"A": "/home/user/code/relevance_prediction/output/ranking_performance/ranking_performance.nist.dl19-passage.json", "B": "/home/user/code/relevance_prediction/output/ranking_performance/ranking_performance.rank1-7b.dl19-passage/0.96.json"}, "metrics": {"ndcg@10": {"kendall_tau": 0.8528528528528528, "kendall_tau_p": 1.0958355703875995e-13, "spearman_rho": 0.9615931721194878, "spearman_rho_p": 3.095035855301447e-21}, "map@100": {"kendall_tau": 0.9099099099099098, "kendall_tau_p": 2.266785348502027e-15, "spearman_rho": 0.9822190611664294, "spearman_rho_p": 5.1112726937084604e-27}, "mrr@10": {"kendall_tau": 0.8347172188586224, "kendall_tau_p": 4.589068655265418e-13, "spearman_rho": 0.9524458955373467, "spearman_rho_p": 1.209743137794585e-19}}}, "0.34": {"n_systems": 37, "files": {"A": "/home/user/code/relevance_prediction/output/ranking_performance/ranking_performance.nist.dl19-passage.json", "B": "/home/user/code/relevance_prediction/output/ranking_performance/ranking_performance.rank1-7b.dl19-passage/0.34.json"}, "metrics": {"ndcg@10": {"kendall_tau": 0.867867867867868, "kendall_tau_p": 4.043315021590678e-14, "spearman_rho": 0.9665718349928876, "spearman_rho_p": 2.8355618337835503e-22}, "map@100": {"kendall_tau": 0.897897897897898, "kendall_tau_p": 5.233421599100931e-15, "spearman_rho": 0.9796111901375059, "spearman_rho_p": 5.492427427607869e-26}, "mrr@10": {"kendall_tau": 0.8347172188586224, "kendall_tau_p": 4.589068655265418e-13, "spearman_rho": 0.9524458955373467, "spearman_rho_p": 1.209743137794585e-19}}}, "0.05": {"n_systems": 37, "files": {"A": "/home/user/code/relevance_prediction/output/ranking_performance/ranking_performance.nist.dl19-passage.json", "B": "/home/user/code/relevance_prediction/output/ranking_performance/ranking_performance.rank1-7b.dl19-passage/0.05.json"}, "metrics": {"ndcg@10": {"kendall_tau": 0.8648648648648649, "kendall_tau_p": 4.942240688409104e-14, "spearman_rho": 0.966808914177335, "spearman_rho_p": 2.5081935676677177e-22}, "map@100": {"kendall_tau": 0.9069069069069069, "kendall_tau_p": 2.7970060241623902e-15, "spearman_rho": 0.9810336652441916, "spearman_rho_p": 1.5666807959650767e-26}, "mrr@10": {"kendall_tau": 0.8347172188586224, "kendall_tau_p": 4.589068655265418e-13, "spearman_rho": 0.9510228300145368, "spearman_rho_p": 2.0038360730086745e-19}}}, "0.42": {"n_systems": 37, "files": {"A": "/home/user/code/relevance_prediction/output/ranking_performance/ranking_performance.nist.dl19-passage.json", "B": "/home/user/code/relevance_prediction/output/ranking_performance/ranking_performance.rank1-7b.dl19-passage/0.42.json"}, "metrics": {"ndcg@10": {"kendall_tau": 0.867867867867868, "kendall_tau_p": 4.043315021590678e-14, "spearman_rho": 0.9665718349928876, "spearman_rho_p": 2.8355618337835503e-22}, "map@100": {"kendall_tau": 0.897897897897898, "kendall_tau_p": 5.233421599100931e-15, "spearman_rho": 0.9796111901375059, "spearman_rho_p": 5.492427427607869e-26}, "mrr@10": {"kendall_tau": 0.8347172188586224, "kendall_tau_p": 4.589068655265418e-13, "spearman_rho": 0.9524458955373467, "spearman_rho_p": 1.209743137794585e-19}}}, "0.09": {"n_systems": 37, "files": {"A": "/home/user/code/relevance_prediction/output/ranking_performance/ranking_performance.nist.dl19-passage.json", "B": "/home/user/code/relevance_prediction/output/ranking_performance/ranking_performance.rank1-7b.dl19-passage/0.09.json"}, "metrics": {"ndcg@10": {"kendall_tau": 0.8588588588588588, "kendall_tau_p": 7.369182830354849e-14, "spearman_rho": 0.9653864390706496, "spearman_rho_p": 5.168915433401108e-22}, "map@100": {"kendall_tau": 0.9069069069069069, "kendall_tau_p": 2.7970060241623902e-15, "spearman_rho": 0.9810336652441916, "spearman_rho_p": 1.5666807959650767e-26}, "mrr@10": {"kendall_tau": 0.8316983500743235, "kendall_tau_p": 5.563603535575372e-13, "spearman_rho": 0.9512600076016718, "spearman_rho_p": 1.8441240005327494e-19}}}, "0.38": {"n_systems": 37, "files": {"A": "/home/user/code/relevance_prediction/output/ranking_performance/ranking_performance.nist.dl19-passage.json", "B": "/home/user/code/relevance_prediction/output/ranking_performance/ranking_performance.rank1-7b.dl19-passage/0.38.json"}, "metrics": {"ndcg@10": {"kendall_tau": 0.867867867867868, "kendall_tau_p": 4.043315021590678e-14, "spearman_rho": 0.9665718349928876, "spearman_rho_p": 2.8355618337835503e-22}, "map@100": {"kendall_tau": 0.897897897897898, "kendall_tau_p": 5.233421599100931e-15, "spearman_rho": 0.9796111901375059, "spearman_rho_p": 5.492427427607869e-26}, "mrr@10": {"kendall_tau": 0.8347172188586224, "kendall_tau_p": 4.589068655265418e-13, "spearman_rho": 0.9524458955373467, "spearman_rho_p": 1.209743137794585e-19}}}, "0.73": {"n_systems": 37, "files": {"A": "/home/user/code/relevance_prediction/output/ranking_performance/ranking_performance.nist.dl19-passage.json", "B": "/home/user/code/relevance_prediction/output/ranking_performance/ranking_performance.rank1-7b.dl19-passage/0.73.json"}, "metrics": {"ndcg@10": {"kendall_tau": 0.8558558558558559, "kendall_tau_p": 8.989354747556581e-14, "spearman_rho": 0.9623044096728307, "spearman_rho_p": 2.2441673781450668e-21}, "map@100": {"kendall_tau": 0.903903903903904, "kendall_tau_p": 3.4489238579727526e-15, "spearman_rho": 0.9810336652441916, "spearman_rho_p": 1.5666807959650767e-26}, "mrr@10": {"kendall_tau": 0.8347172188586224, "kendall_tau_p": 4.589068655265418e-13, "spearman_rho": 0.9524458955373467, "spearman_rho_p": 1.209743137794585e-19}}}, "0.11": {"n_systems": 37, "files": {"A": "/home/user/code/relevance_prediction/output/ranking_performance/ranking_performance.nist.dl19-passage.json", "B": "/home/user/code/relevance_prediction/output/ranking_performance/ranking_performance.rank1-7b.dl19-passage/0.11.json"}, "metrics": {"ndcg@10": {"kendall_tau": 0.8648648648648649, "kendall_tau_p": 4.942240688409104e-14, "spearman_rho": 0.9663347558084399, "spearman_rho_p": 3.2028368331837816e-22}, "map@100": {"kendall_tau": 0.903903903903904, "kendall_tau_p": 3.4489238579727526e-15, "spearman_rho": 0.980796586059744, "spearman_rho_p": 1.943493430675664e-26}, "mrr@10": {"kendall_tau": 0.8316983500743235, "kendall_tau_p": 5.563603535575372e-13, "spearman_rho": 0.9512600076016718, "spearman_rho_p": 1.8441240005327494e-19}}}, "0.7": {"n_systems": 37, "files": {"A": "/home/user/code/relevance_prediction/output/ranking_performance/ranking_performance.nist.dl19-passage.json", "B": "/home/user/code/relevance_prediction/output/ranking_performance/ranking_performance.rank1-7b.dl19-passage/0.7.json"}, "metrics": {"ndcg@10": {"kendall_tau": 0.8558558558558559, "kendall_tau_p": 8.989354747556581e-14, "spearman_rho": 0.9623044096728307, "spearman_rho_p": 2.2441673781450668e-21}, "map@100": {"kendall_tau": 0.903903903903904, "kendall_tau_p": 3.4489238579727526e-15, "spearman_rho": 0.9810336652441916, "spearman_rho_p": 1.5666807959650767e-26}, "mrr@10": {"kendall_tau": 0.8347172188586224, "kendall_tau_p": 4.589068655265418e-13, "spearman_rho": 0.9524458955373467, "spearman_rho_p": 1.209743137794585e-19}}}, "0.82": {"n_systems": 37, "files": {"A": "/home/user/code/relevance_prediction/output/ranking_performance/ranking_performance.nist.dl19-passage.json", "B": "/home/user/code/relevance_prediction/output/ranking_performance/ranking_performance.rank1-7b.dl19-passage/0.82.json"}, "metrics": {"ndcg@10": {"kendall_tau": 0.8558558558558559, "kendall_tau_p": 8.989354747556581e-14, "spearman_rho": 0.9623044096728307, "spearman_rho_p": 2.2441673781450668e-21}, "map@100": {"kendall_tau": 0.9009009009009009, "kendall_tau_p": 4.249922767583786e-15, "spearman_rho": 0.980796586059744, "spearman_rho_p": 1.943493430675664e-26}, "mrr@10": {"kendall_tau": 0.8347172188586224, "kendall_tau_p": 4.589068655265418e-13, "spearman_rho": 0.9524458955373467, "spearman_rho_p": 1.209743137794585e-19}}}, "0.77": {"n_systems": 37, "files": {"A": "/home/user/code/relevance_prediction/output/ranking_performance/ranking_performance.nist.dl19-passage.json", "B": "/home/user/code/relevance_prediction/output/ranking_performance/ranking_performance.rank1-7b.dl19-passage/0.77.json"}, "metrics": {"ndcg@10": {"kendall_tau": 0.8558558558558559, "kendall_tau_p": 8.989354747556581e-14, "spearman_rho": 0.9623044096728307, "spearman_rho_p": 2.2441673781450668e-21}, "map@100": {"kendall_tau": 0.9009009009009009, "kendall_tau_p": 4.249922767583786e-15, "spearman_rho": 0.980796586059744, "spearman_rho_p": 1.943493430675664e-26}, "mrr@10": {"kendall_tau": 0.8347172188586224, "kendall_tau_p": 4.589068655265418e-13, "spearman_rho": 0.9524458955373467, "spearman_rho_p": 1.209743137794585e-19}}}, "0.46": {"n_systems": 37, "files": {"A": "/home/user/code/relevance_prediction/output/ranking_performance/ranking_performance.nist.dl19-passage.json", "B": "/home/user/code/relevance_prediction/output/ranking_performance/ranking_performance.rank1-7b.dl19-passage/0.46.json"}, "metrics": {"ndcg@10": {"kendall_tau": 0.867867867867868, "kendall_tau_p": 4.043315021590678e-14, "spearman_rho": 0.9665718349928876, "spearman_rho_p": 2.8355618337835503e-22}, "map@100": {"kendall_tau": 0.897897897897898, "kendall_tau_p": 5.233421599100931e-15, "spearman_rho": 0.9796111901375059, "spearman_rho_p": 5.492427427607869e-26}, "mrr@10": {"kendall_tau": 0.8347172188586224, "kendall_tau_p": 4.589068655265418e-13, "spearman_rho": 0.9524458955373467, "spearman_rho_p": 1.209743137794585e-19}}}, "0.24": {"n_systems": 37, "files": {"A": "/home/user/code/relevance_prediction/output/ranking_performance/ranking_performance.nist.dl19-passage.json", "B": "/home/user/code/relevance_prediction/output/ranking_performance/ranking_performance.rank1-7b.dl19-passage/0.24.json"}, "metrics": {"ndcg@10": {"kendall_tau": 0.8648648648648649, "kendall_tau_p": 4.942240688409104e-14, "spearman_rho": 0.9646752015173067, "spearman_rho_p": 7.337277858783105e-22}, "map@100": {"kendall_tau": 0.8948948948948949, "kendall_tau_p": 6.440175279163034e-15, "spearman_rho": 0.9788999525841631, "spearman_rho_p": 9.95252340421051e-26}, "mrr@10": {"kendall_tau": 0.8316983500743235, "kendall_tau_p": 5.563603535575372e-13, "spearman_rho": 0.9517343627759418, "spearman_rho_p": 1.5599261236667657e-19}}}, "0.86": {"n_systems": 37, "files": {"A": "/home/user/code/relevance_prediction/output/ranking_performance/ranking_performance.nist.dl19-passage.json", "B": "/home/user/code/relevance_prediction/output/ranking_performance/ranking_performance.rank1-7b.dl19-passage/0.86.json"}, "metrics": {"ndcg@10": {"kendall_tau": 0.8528528528528528, "kendall_tau_p": 1.0958355703875995e-13, "spearman_rho": 0.9615931721194878, "spearman_rho_p": 3.095035855301447e-21}, "map@100": {"kendall_tau": 0.9009009009009009, "kendall_tau_p": 4.249922767583786e-15, "spearman_rho": 0.980796586059744, "spearman_rho_p": 1.943493430675664e-26}, "mrr@10": {"kendall_tau": 0.8347172188586224, "kendall_tau_p": 4.589068655265418e-13, "spearman_rho": 0.9524458955373467, "spearman_rho_p": 1.209743137794585e-19}}}, "0.15": {"n_systems": 37, "files": {"A": "/home/user/code/relevance_prediction/output/ranking_performance/ranking_performance.nist.dl19-passage.json", "B": "/home/user/code/relevance_prediction/output/ranking_performance/ranking_performance.rank1-7b.dl19-passage/0.15.json"}, "metrics": {"ndcg@10": {"kendall_tau": 0.867867867867868, "kendall_tau_p": 4.043315021590678e-14, "spearman_rho": 0.9656235182550972, "spearman_rho_p": 4.591776137133823e-22}, "map@100": {"kendall_tau": 0.897897897897898, "kendall_tau_p": 5.233421599100931e-15, "spearman_rho": 0.9791370317686106, "spearman_rho_p": 8.182123953070416e-26}, "mrr@10": {"kendall_tau": 0.8316983500743235, "kendall_tau_p": 5.563603535575372e-13, "spearman_rho": 0.9517343627759418, "spearman_rho_p": 1.5599261236667657e-19}}}, "0.3": {"n_systems": 37, "files": {"A": "/home/user/code/relevance_prediction/output/ranking_performance/ranking_performance.nist.dl19-passage.json", "B": "/home/user/code/relevance_prediction/output/ranking_performance/ranking_performance.rank1-7b.dl19-passage/0.3.json"}, "metrics": {"ndcg@10": {"kendall_tau": 0.8738738738738738, "kendall_tau_p": 2.700770114420909e-14, "spearman_rho": 0.9684684684684685, "spearman_rho_p": 1.0356955031590111e-22}, "map@100": {"kendall_tau": 0.9009009009009009, "kendall_tau_p": 4.249922767583786e-15, "spearman_rho": 0.9810336652441916, "spearman_rho_p": 1.5666807959650767e-26}, "mrr@10": {"kendall_tau": 0.8347172188586224, "kendall_tau_p": 4.589068655265418e-13, "spearman_rho": 0.9524458955373467, "spearman_rho_p": 1.209743137794585e-19}}}, "0.08": {"n_systems": 37, "files": {"A": "/home/user/code/relevance_prediction/output/ranking_performance/ranking_performance.nist.dl19-passage.json", "B": "/home/user/code/relevance_prediction/output/ranking_performance/ranking_performance.rank1-7b.dl19-passage/0.08.json"}, "metrics": {"ndcg@10": {"kendall_tau": 0.8588588588588588, "kendall_tau_p": 7.369182830354849e-14, "spearman_rho": 0.9653864390706496, "spearman_rho_p": 5.168915433401108e-22}, "map@100": {"kendall_tau": 0.9069069069069069, "kendall_tau_p": 2.7970060241623902e-15, "spearman_rho": 0.9810336652441916, "spearman_rho_p": 1.5666807959650767e-26}, "mrr@10": {"kendall_tau": 0.8316983500743235, "kendall_tau_p": 5.563603535575372e-13, "spearman_rho": 0.9512600076016718, "spearman_rho_p": 1.8441240005327494e-19}}}, "0.43": {"n_systems": 37, "files": {"A": "/home/user/code/relevance_prediction/output/ranking_performance/ranking_performance.nist.dl19-passage.json", "B": "/home/user/code/relevance_prediction/output/ranking_performance/ranking_performance.rank1-7b.dl19-passage/0.43.json"}, "metrics": {"ndcg@10": {"kendall_tau": 0.867867867867868, "kendall_tau_p": 4.043315021590678e-14, "spearman_rho": 0.9665718349928876, "spearman_rho_p": 2.8355618337835503e-22}, "map@100": {"kendall_tau": 0.897897897897898, "kendall_tau_p": 5.233421599100931e-15, "spearman_rho": 0.9796111901375059, "spearman_rho_p": 5.492427427607869e-26}, "mrr@10": {"kendall_tau": 0.8347172188586224, "kendall_tau_p": 4.589068655265418e-13, "spearman_rho": 0.9524458955373467, "spearman_rho_p": 1.209743137794585e-19}}}, "0.72": {"n_systems": 37, "files": {"A": "/home/user/code/relevance_prediction/output/ranking_performance/ranking_performance.nist.dl19-passage.json", "B": "/home/user/code/relevance_prediction/output/ranking_performance/ranking_performance.rank1-7b.dl19-passage/0.72.json"}, "metrics": {"ndcg@10": {"kendall_tau": 0.8558558558558559, "kendall_tau_p": 8.989354747556581e-14, "spearman_rho": 0.9623044096728307, "spearman_rho_p": 2.2441673781450668e-21}, "map@100": {"kendall_tau": 0.903903903903904, "kendall_tau_p": 3.4489238579727526e-15, "spearman_rho": 0.9810336652441916, "spearman_rho_p": 1.5666807959650767e-26}, "mrr@10": {"kendall_tau": 0.8347172188586224, "kendall_tau_p": 4.589068655265418e-13, "spearman_rho": 0.9524458955373467, "spearman_rho_p": 1.209743137794585e-19}}}, "0.39": {"n_systems": 37, "files": {"A": "/home/user/code/relevance_prediction/output/ranking_performance/ranking_performance.nist.dl19-passage.json", "B": "/home/user/code/relevance_prediction/output/ranking_performance/ranking_performance.rank1-7b.dl19-passage/0.39.json"}, "metrics": {"ndcg@10": {"kendall_tau": 0.867867867867868, "kendall_tau_p": 4.043315021590678e-14, "spearman_rho": 0.9665718349928876, "spearman_rho_p": 2.8355618337835503e-22}, "map@100": {"kendall_tau": 0.897897897897898, "kendall_tau_p": 5.233421599100931e-15, "spearman_rho": 0.9796111901375059, "spearman_rho_p": 5.492427427607869e-26}, "mrr@10": {"kendall_tau": 0.8347172188586224, "kendall_tau_p": 4.589068655265418e-13, "spearman_rho": 0.9524458955373467, "spearman_rho_p": 1.209743137794585e-19}}}, "1.0": {"n_systems": 37, "files": {"A": "/home/user/code/relevance_prediction/output/ranking_performance/ranking_performance.nist.dl19-passage.json", "B": "/home/user/code/relevance_prediction/output/ranking_performance/ranking_performance.rank1-7b.dl19-passage/1.0.json"}, "metrics": {"ndcg@10": {"kendall_tau": NaN, "kendall_tau_p": NaN, "spearman_rho": NaN, "spearman_rho_p": NaN}, "map@100": {"kendall_tau": NaN, "kendall_tau_p": NaN, "spearman_rho": NaN, "spearman_rho_p": NaN}, "mrr@10": {"kendall_tau": NaN, "kendall_tau_p": NaN, "spearman_rho": NaN, "spearman_rho_p": NaN}}}, "0.6": {"n_systems": 37, "files": {"A": "/home/user/code/relevance_prediction/output/ranking_performance/ranking_performance.nist.dl19-passage.json", "B": "/home/user/code/relevance_prediction/output/ranking_performance/ranking_performance.rank1-7b.dl19-passage/0.6.json"}, "metrics": {"ndcg@10": {"kendall_tau": 0.8468468468468467, "kendall_tau_p": 1.625183200282792e-13, "spearman_rho": 0.9601706970128023, "spearman_rho_p": 5.783059808490516e-21}, "map@100": {"kendall_tau": 0.897897897897898, "kendall_tau_p": 5.233421599100931e-15, "spearman_rho": 0.9803224276908485, "spearman_rho_p": 2.9671574948533413e-26}, "mrr@10": {"kendall_tau": 0.8347172188586224, "kendall_tau_p": 4.589068655265418e-13, "spearman_rho": 0.9524458955373467, "spearman_rho_p": 1.209743137794585e-19}}}, "0.21": {"n_systems": 37, "files": {"A": "/home/user/code/relevance_prediction/output/ranking_performance/ranking_performance.nist.dl19-passage.json", "B": "/home/user/code/relevance_prediction/output/ranking_performance/ranking_performance.rank1-7b.dl19-passage/0.21.json"}, "metrics": {"ndcg@10": {"kendall_tau": 0.8648648648648649, "kendall_tau_p": 4.942240688409104e-14, "spearman_rho": 0.9642010431484115, "spearman_rho_p": 9.23078457180987e-22}, "map@100": {"kendall_tau": 0.897897897897898, "kendall_tau_p": 5.233421599100931e-15, "spearman_rho": 0.9791370317686106, "spearman_rho_p": 8.182123953070416e-26}, "mrr@10": {"kendall_tau": 0.8316983500743235, "kendall_tau_p": 5.563603535575372e-13, "spearman_rho": 0.9517343627759418, "spearman_rho_p": 1.5599261236667657e-19}}}, "0.83": {"n_systems": 37, "files": {"A": "/home/user/code/relevance_prediction/output/ranking_performance/ranking_performance.nist.dl19-passage.json", "B": "/home/user/code/relevance_prediction/output/ranking_performance/ranking_performance.rank1-7b.dl19-passage/0.83.json"}, "metrics": {"ndcg@10": {"kendall_tau": 0.8558558558558559, "kendall_tau_p": 8.989354747556581e-14, "spearman_rho": 0.9623044096728307, "spearman_rho_p": 2.2441673781450668e-21}, "map@100": {"kendall_tau": 0.9009009009009009, "kendall_tau_p": 4.249922767583786e-15, "spearman_rho": 0.980796586059744, "spearman_rho_p": 1.943493430675664e-26}, "mrr@10": {"kendall_tau": 0.8347172188586224, "kendall_tau_p": 4.589068655265418e-13, "spearman_rho": 0.9524458955373467, "spearman_rho_p": 1.209743137794585e-19}}}, "0.76": {"n_systems": 37, "files": {"A": "/home/user/code/relevance_prediction/output/ranking_performance/ranking_performance.nist.dl19-passage.json", "B": "/home/user/code/relevance_prediction/output/ranking_performance/ranking_performance.rank1-7b.dl19-passage/0.76.json"}, "metrics": {"ndcg@10": {"kendall_tau": 0.8558558558558559, "kendall_tau_p": 8.989354747556581e-14, "spearman_rho": 0.9623044096728307, "spearman_rho_p": 2.2441673781450668e-21}, "map@100": {"kendall_tau": 0.9009009009009009, "kendall_tau_p": 4.249922767583786e-15, "spearman_rho": 0.980796586059744, "spearman_rho_p": 1.943493430675664e-26}, "mrr@10": {"kendall_tau": 0.8347172188586224, "kendall_tau_p": 4.589068655265418e-13, "spearman_rho": 0.9524458955373467, "spearman_rho_p": 1.209743137794585e-19}}}, "0.47": {"n_systems": 37, "files": {"A": "/home/user/code/relevance_prediction/output/ranking_performance/ranking_performance.nist.dl19-passage.json", "B": "/home/user/code/relevance_prediction/output/ranking_performance/ranking_performance.rank1-7b.dl19-passage/0.47.json"}, "metrics": {"ndcg@10": {"kendall_tau": 0.867867867867868, "kendall_tau_p": 4.043315021590678e-14, "spearman_rho": 0.9665718349928876, "spearman_rho_p": 2.8355618337835503e-22}, "map@100": {"kendall_tau": 0.897897897897898, "kendall_tau_p": 5.233421599100931e-15, "spearman_rho": 0.9796111901375059, "spearman_rho_p": 5.492427427607869e-26}, "mrr@10": {"kendall_tau": 0.8347172188586224, "kendall_tau_p": 4.589068655265418e-13, "spearman_rho": 0.9524458955373467, "spearman_rho_p": 1.209743137794585e-19}}}, "0.25": {"n_systems": 37, "files": {"A": "/home/user/code/relevance_prediction/output/ranking_performance/ranking_performance.nist.dl19-passage.json", "B": "/home/user/code/relevance_prediction/output/ranking_performance/ranking_performance.rank1-7b.dl19-passage/0.25.json"}, "metrics": {"ndcg@10": {"kendall_tau": 0.8648648648648649, "kendall_tau_p": 4.942240688409104e-14, "spearman_rho": 0.9646752015173067, "spearman_rho_p": 7.337277858783105e-22}, "map@100": {"kendall_tau": 0.8948948948948949, "kendall_tau_p": 6.440175279163034e-15, "spearman_rho": 0.9788999525841631, "spearman_rho_p": 9.95252340421051e-26}, "mrr@10": {"kendall_tau": 0.8316983500743235, "kendall_tau_p": 5.563603535575372e-13, "spearman_rho": 0.9517343627759418, "spearman_rho_p": 1.5599261236667657e-19}}}, "0.87": {"n_systems": 37, "files": {"A": "/home/user/code/relevance_prediction/output/ranking_performance/ranking_performance.nist.dl19-passage.json", "B": "/home/user/code/relevance_prediction/output/ranking_performance/ranking_performance.rank1-7b.dl19-passage/0.87.json"}, "metrics": {"ndcg@10": {"kendall_tau": 0.8528528528528528, "kendall_tau_p": 1.0958355703875995e-13, "spearman_rho": 0.9615931721194878, "spearman_rho_p": 3.095035855301447e-21}, "map@100": {"kendall_tau": 0.9009009009009009, "kendall_tau_p": 4.249922767583786e-15, "spearman_rho": 0.980796586059744, "spearman_rho_p": 1.943493430675664e-26}, "mrr@10": {"kendall_tau": 0.8347172188586224, "kendall_tau_p": 4.589068655265418e-13, "spearman_rho": 0.9524458955373467, "spearman_rho_p": 1.209743137794585e-19}}}, "0.2": {"n_systems": 37, "files": {"A": "/home/user/code/relevance_prediction/output/ranking_performance/ranking_performance.nist.dl19-passage.json", "B": "/home/user/code/relevance_prediction/output/ranking_performance/ranking_performance.rank1-7b.dl19-passage/0.2.json"}, "metrics": {"ndcg@10": {"kendall_tau": 0.8648648648648649, "kendall_tau_p": 4.942240688409104e-14, "spearman_rho": 0.9642010431484115, "spearman_rho_p": 9.23078457180987e-22}, "map@100": {"kendall_tau": 0.897897897897898, "kendall_tau_p": 5.233421599100931e-15, "spearman_rho": 0.9791370317686106, "spearman_rho_p": 8.182123953070416e-26}, "mrr@10": {"kendall_tau": 0.8316983500743235, "kendall_tau_p": 5.563603535575372e-13, "spearman_rho": 0.9517343627759418, "spearman_rho_p": 1.5599261236667657e-19}}}, "0.14": {"n_systems": 37, "files": {"A": "/home/user/code/relevance_prediction/output/ranking_performance/ranking_performance.nist.dl19-passage.json", "B": "/home/user/code/relevance_prediction/output/ranking_performance/ranking_performance.rank1-7b.dl19-passage/0.14.json"}, "metrics": {"ndcg@10": {"kendall_tau": 0.8618618618618619, "kendall_tau_p": 6.036953062344684e-14, "spearman_rho": 0.9642010431484115, "spearman_rho_p": 9.23078457180987e-22}, "map@100": {"kendall_tau": 0.897897897897898, "kendall_tau_p": 5.233421599100931e-15, "spearman_rho": 0.9791370317686106, "spearman_rho_p": 8.182123953070416e-26}, "mrr@10": {"kendall_tau": 0.8316983500743235, "kendall_tau_p": 5.563603535575372e-13, "spearman_rho": 0.9512600076016718, "spearman_rho_p": 1.8441240005327494e-19}}}, "0.53": {"n_systems": 37, "files": {"A": "/home/user/code/relevance_prediction/output/ranking_performance/ranking_performance.nist.dl19-passage.json", "B": "/home/user/code/relevance_prediction/output/ranking_performance/ranking_performance.rank1-7b.dl19-passage/0.53.json"}, "metrics": {"ndcg@10": {"kendall_tau": 0.8528528528528528, "kendall_tau_p": 1.0958355703875995e-13, "spearman_rho": 0.9615931721194878, "spearman_rho_p": 3.095035855301447e-21}, "map@100": {"kendall_tau": 0.897897897897898, "kendall_tau_p": 5.233421599100931e-15, "spearman_rho": 0.9803224276908485, "spearman_rho_p": 2.9671574948533413e-26}, "mrr@10": {"kendall_tau": 0.8347172188586224, "kendall_tau_p": 4.589068655265418e-13, "spearman_rho": 0.9524458955373467, "spearman_rho_p": 1.209743137794585e-19}}}, "0.18": {"n_systems": 37, "files": {"A": "/home/user/code/relevance_prediction/output/ranking_performance/ranking_performance.nist.dl19-passage.json", "B": "/home/user/code/relevance_prediction/output/ranking_performance/ranking_performance.rank1-7b.dl19-passage/0.18.json"}, "metrics": {"ndcg@10": {"kendall_tau": 0.8648648648648649, "kendall_tau_p": 4.942240688409104e-14, "spearman_rho": 0.9642010431484115, "spearman_rho_p": 9.23078457180987e-22}, "map@100": {"kendall_tau": 0.897897897897898, "kendall_tau_p": 5.233421599100931e-15, "spearman_rho": 0.9791370317686106, "spearman_rho_p": 8.182123953070416e-26}, "mrr@10": {"kendall_tau": 0.8316983500743235, "kendall_tau_p": 5.563603535575372e-13, "spearman_rho": 0.9517343627759418, "spearman_rho_p": 1.5599261236667657e-19}}}, "0.29": {"n_systems": 37, "files": {"A": "/home/user/code/relevance_prediction/output/ranking_performance/ranking_performance.nist.dl19-passage.json", "B": "/home/user/code/relevance_prediction/output/ranking_performance/ranking_performance.rank1-7b.dl19-passage/0.29.json"}, "metrics": {"ndcg@10": {"kendall_tau": 0.8738738738738738, "kendall_tau_p": 2.700770114420909e-14, "spearman_rho": 0.9684684684684685, "spearman_rho_p": 1.0356955031590111e-22}, "map@100": {"kendall_tau": 0.9009009009009009, "kendall_tau_p": 4.249922767583786e-15, "spearman_rho": 0.9810336652441916, "spearman_rho_p": 1.5666807959650767e-26}, "mrr@10": {"kendall_tau": 0.8347172188586224, "kendall_tau_p": 4.589068655265418e-13, "spearman_rho": 0.9524458955373467, "spearman_rho_p": 1.209743137794585e-19}}}, "0.62": {"n_systems": 37, "files": {"A": "/home/user/code/relevance_prediction/output/ranking_performance/ranking_performance.nist.dl19-passage.json", "B": "/home/user/code/relevance_prediction/output/ranking_performance/ranking_performance.rank1-7b.dl19-passage/0.62.json"}, "metrics": {"ndcg@10": {"kendall_tau": 0.8558558558558559, "kendall_tau_p": 8.989354747556581e-14, "spearman_rho": 0.9623044096728307, "spearman_rho_p": 2.2441673781450668e-21}, "map@100": {"kendall_tau": 0.9009009009009009, "kendall_tau_p": 4.249922767583786e-15, "spearman_rho": 0.980796586059744, "spearman_rho_p": 1.943493430675664e-26}, "mrr@10": {"kendall_tau": 0.8347172188586224, "kendall_tau_p": 4.589068655265418e-13, "spearman_rho": 0.9524458955373467, "spearman_rho_p": 1.209743137794585e-19}}}, "0.93": {"n_systems": 37, "files": {"A": "/home/user/code/relevance_prediction/output/ranking_performance/ranking_performance.nist.dl19-passage.json", "B": "/home/user/code/relevance_prediction/output/ranking_performance/ranking_performance.rank1-7b.dl19-passage/0.93.json"}, "metrics": {"ndcg@10": {"kendall_tau": 0.8498498498498499, "kendall_tau_p": 1.3349653228005416e-13, "spearman_rho": 0.9611190137505926, "spearman_rho_p": 3.8219476497508666e-21}, "map@100": {"kendall_tau": 0.897897897897898, "kendall_tau_p": 5.233421599100931e-15, "spearman_rho": 0.9798482693219533, "spearman_rho_p": 4.48418548500829e-26}, "mrr@10": {"kendall_tau": 0.8347172188586224, "kendall_tau_p": 4.589068655265418e-13, "spearman_rho": 0.9524458955373467, "spearman_rho_p": 1.209743137794585e-19}}}, "0.31": {"n_systems": 37, "files": {"A": "/home/user/code/relevance_prediction/output/ranking_performance/ranking_performance.nist.dl19-passage.json", "B": "/home/user/code/relevance_prediction/output/ranking_performance/ranking_performance.rank1-7b.dl19-passage/0.31.json"}, "metrics": {"ndcg@10": {"kendall_tau": 0.8738738738738738, "kendall_tau_p": 2.700770114420909e-14, "spearman_rho": 0.9684684684684685, "spearman_rho_p": 1.0356955031590111e-22}, "map@100": {"kendall_tau": 0.9009009009009009, "kendall_tau_p": 4.249922767583786e-15, "spearman_rho": 0.9810336652441916, "spearman_rho_p": 1.5666807959650767e-26}, "mrr@10": {"kendall_tau": 0.8347172188586224, "kendall_tau_p": 4.589068655265418e-13, "spearman_rho": 0.9524458955373467, "spearman_rho_p": 1.209743137794585e-19}}}, "0.66": {"n_systems": 37, "files": {"A": "/home/user/code/relevance_prediction/output/ranking_performance/ranking_performance.nist.dl19-passage.json", "B": "/home/user/code/relevance_prediction/output/ranking_performance/ranking_performance.rank1-7b.dl19-passage/0.66.json"}, "metrics": {"ndcg@10": {"kendall_tau": 0.8558558558558559, "kendall_tau_p": 8.989354747556581e-14, "spearman_rho": 0.9623044096728307, "spearman_rho_p": 2.2441673781450668e-21}, "map@100": {"kendall_tau": 0.9009009009009009, "kendall_tau_p": 4.249922767583786e-15, "spearman_rho": 0.980796586059744, "spearman_rho_p": 1.943493430675664e-26}, "mrr@10": {"kendall_tau": 0.8347172188586224, "kendall_tau_p": 4.589068655265418e-13, "spearman_rho": 0.9524458955373467, "spearman_rho_p": 1.209743137794585e-19}}}, "0.57": {"n_systems": 37, "files": {"A": "/home/user/code/relevance_prediction/output/ranking_performance/ranking_performance.nist.dl19-passage.json", "B": "/home/user/code/relevance_prediction/output/ranking_performance/ranking_performance.rank1-7b.dl19-passage/0.57.json"}, "metrics": {"ndcg@10": {"kendall_tau": 0.8468468468468467, "kendall_tau_p": 1.625183200282792e-13, "spearman_rho": 0.9601706970128023, "spearman_rho_p": 5.783059808490516e-21}, "map@100": {"kendall_tau": 0.897897897897898, "kendall_tau_p": 5.233421599100931e-15, "spearman_rho": 0.9803224276908485, "spearman_rho_p": 2.9671574948533413e-26}, "mrr@10": {"kendall_tau": 0.8347172188586224, "kendall_tau_p": 4.589068655265418e-13, "spearman_rho": 0.9524458955373467, "spearman_rho_p": 1.209743137794585e-19}}}, "0.97": {"n_systems": 37, "files": {"A": "/home/user/code/relevance_prediction/output/ranking_performance/ranking_performance.nist.dl19-passage.json", "B": "/home/user/code/relevance_prediction/output/ranking_performance/ranking_performance.rank1-7b.dl19-passage/0.97.json"}, "metrics": {"ndcg@10": {"kendall_tau": 0.8528528528528528, "kendall_tau_p": 1.0958355703875995e-13, "spearman_rho": 0.9615931721194878, "spearman_rho_p": 3.095035855301447e-21}, "map@100": {"kendall_tau": 0.9099099099099098, "kendall_tau_p": 2.266785348502027e-15, "spearman_rho": 0.9822190611664294, "spearman_rho_p": 5.1112726937084604e-27}, "mrr@10": {"kendall_tau": 0.8347172188586224, "kendall_tau_p": 4.589068655265418e-13, "spearman_rho": 0.9524458955373467, "spearman_rho_p": 1.209743137794585e-19}}}, "0.35": {"n_systems": 37, "files": {"A": "/home/user/code/relevance_prediction/output/ranking_performance/ranking_performance.nist.dl19-passage.json", "B": "/home/user/code/relevance_prediction/output/ranking_performance/ranking_performance.rank1-7b.dl19-passage/0.35.json"}, "metrics": {"ndcg@10": {"kendall_tau": 0.867867867867868, "kendall_tau_p": 4.043315021590678e-14, "spearman_rho": 0.9665718349928876, "spearman_rho_p": 2.8355618337835503e-22}, "map@100": {"kendall_tau": 0.897897897897898, "kendall_tau_p": 5.233421599100931e-15, "spearman_rho": 0.9796111901375059, "spearman_rho_p": 5.492427427607869e-26}, "mrr@10": {"kendall_tau": 0.8347172188586224, "kendall_tau_p": 4.589068655265418e-13, "spearman_rho": 0.9524458955373467, "spearman_rho_p": 1.209743137794585e-19}}}, "0.04": {"n_systems": 37, "files": {"A": "/home/user/code/relevance_prediction/output/ranking_performance/ranking_performance.nist.dl19-passage.json", "B": "/home/user/code/relevance_prediction/output/ranking_performance/ranking_performance.rank1-7b.dl19-passage/0.04.json"}, "metrics": {"ndcg@10": {"kendall_tau": 0.8738738738738738, "kendall_tau_p": 2.700770114420909e-14, "spearman_rho": 0.9696538643907064, "spearman_rho_p": 5.346595143717353e-23}, "map@100": {"kendall_tau": 0.9069069069069069, "kendall_tau_p": 2.7970060241623902e-15, "spearman_rho": 0.9810336652441916, "spearman_rho_p": 1.5666807959650767e-26}, "mrr@10": {"kendall_tau": 0.84075495642722, "kendall_tau_p": 3.1159042035603546e-13, "spearman_rho": 0.9543433162344267, "spearman_rho_p": 6.022796807655077e-20}}}, "0.41": {"n_systems": 37, "files": {"A": "/home/user/code/relevance_prediction/output/ranking_performance/ranking_performance.nist.dl19-passage.json", "B": "/home/user/code/relevance_prediction/output/ranking_performance/ranking_performance.rank1-7b.dl19-passage/0.41.json"}, "metrics": {"ndcg@10": {"kendall_tau": 0.867867867867868, "kendall_tau_p": 4.043315021590678e-14, "spearman_rho": 0.9665718349928876, "spearman_rho_p": 2.8355618337835503e-22}, "map@100": {"kendall_tau": 0.897897897897898, "kendall_tau_p": 5.233421599100931e-15, "spearman_rho": 0.9796111901375059, "spearman_rho_p": 5.492427427607869e-26}, "mrr@10": {"kendall_tau": 0.8347172188586224, "kendall_tau_p": 4.589068655265418e-13, "spearman_rho": 0.9524458955373467, "spearman_rho_p": 1.209743137794585e-19}}}, "0.99": {"n_systems": 37, "files": {"A": "/home/user/code/relevance_prediction/output/ranking_performance/ranking_performance.nist.dl19-passage.json", "B": "/home/user/code/relevance_prediction/output/ranking_performance/ranking_performance.rank1-7b.dl19-passage/0.99.json"}, "metrics": {"ndcg@10": {"kendall_tau": 0.8468468468468467, "kendall_tau_p": 1.625183200282792e-13, "spearman_rho": 0.9613560929350403, "spearman_rho_p": 3.440474023522361e-21}, "map@100": {"kendall_tau": 0.912912912912913, "kendall_tau_p": 1.8358388899482685e-15, "spearman_rho": 0.9829302987197722, "spearman_rho_p": 2.5159690790049984e-27}, "mrr@10": {"kendall_tau": 0.8386123680241327, "kendall_tau_p": 3.449247119366495e-13, "spearman_rho": 0.9539309854144433, "spearman_rho_p": 7.025884512077764e-20}}}, "0.12": {"n_systems": 37, "files": {"A": "/home/user/code/relevance_prediction/output/ranking_performance/ranking_performance.nist.dl19-passage.json", "B": "/home/user/code/relevance_prediction/output/ranking_performance/ranking_performance.rank1-7b.dl19-passage/0.12.json"}, "metrics": {"ndcg@10": {"kendall_tau": 0.8618618618618619, "kendall_tau_p": 6.036953062344684e-14, "spearman_rho": 0.9642010431484115, "spearman_rho_p": 9.23078457180987e-22}, "map@100": {"kendall_tau": 0.9009009009009009, "kendall_tau_p": 4.249922767583786e-15, "spearman_rho": 0.9798482693219533, "spearman_rho_p": 4.48418548500829e-26}, "mrr@10": {"kendall_tau": 0.8316983500743235, "kendall_tau_p": 5.563603535575372e-13, "spearman_rho": 0.9512600076016718, "spearman_rho_p": 1.8441240005327494e-19}}}, "0.59": {"n_systems": 37, "files": {"A": "/home/user/code/relevance_prediction/output/ranking_performance/ranking_performance.nist.dl19-passage.json", "B": "/home/user/code/relevance_prediction/output/ranking_performance/ranking_performance.rank1-7b.dl19-passage/0.59.json"}, "metrics": {"ndcg@10": {"kendall_tau": 0.8468468468468467, "kendall_tau_p": 1.625183200282792e-13, "spearman_rho": 0.9601706970128023, "spearman_rho_p": 5.783059808490516e-21}, "map@100": {"kendall_tau": 0.897897897897898, "kendall_tau_p": 5.233421599100931e-15, "spearman_rho": 0.9803224276908485, "spearman_rho_p": 2.9671574948533413e-26}, "mrr@10": {"kendall_tau": 0.8347172188586224, "kendall_tau_p": 4.589068655265418e-13, "spearman_rho": 0.9524458955373467, "spearman_rho_p": 1.209743137794585e-19}}}, "0.4": {"n_systems": 37, "files": {"A": "/home/user/code/relevance_prediction/output/ranking_performance/ranking_performance.nist.dl19-passage.json", "B": "/home/user/code/relevance_prediction/output/ranking_performance/ranking_performance.rank1-7b.dl19-passage/0.4.json"}, "metrics": {"ndcg@10": {"kendall_tau": 0.867867867867868, "kendall_tau_p": 4.043315021590678e-14, "spearman_rho": 0.9665718349928876, "spearman_rho_p": 2.8355618337835503e-22}, "map@100": {"kendall_tau": 0.897897897897898, "kendall_tau_p": 5.233421599100931e-15, "spearman_rho": 0.9796111901375059, "spearman_rho_p": 5.492427427607869e-26}, "mrr@10": {"kendall_tau": 0.8347172188586224, "kendall_tau_p": 4.589068655265418e-13, "spearman_rho": 0.9524458955373467, "spearman_rho_p": 1.209743137794585e-19}}}, "0.81": {"n_systems": 37, "files": {"A": "/home/user/code/relevance_prediction/output/ranking_performance/ranking_performance.nist.dl19-passage.json", "B": "/home/user/code/relevance_prediction/output/ranking_performance/ranking_performance.rank1-7b.dl19-passage/0.81.json"}, "metrics": {"ndcg@10": {"kendall_tau": 0.8558558558558559, "kendall_tau_p": 8.989354747556581e-14, "spearman_rho": 0.9623044096728307, "spearman_rho_p": 2.2441673781450668e-21}, "map@100": {"kendall_tau": 0.9009009009009009, "kendall_tau_p": 4.249922767583786e-15, "spearman_rho": 0.980796586059744, "spearman_rho_p": 1.943493430675664e-26}, "mrr@10": {"kendall_tau": 0.8347172188586224, "kendall_tau_p": 4.589068655265418e-13, "spearman_rho": 0.9524458955373467, "spearman_rho_p": 1.209743137794585e-19}}}, "0.68": {"n_systems": 37, "files": {"A": "/home/user/code/relevance_prediction/output/ranking_performance/ranking_performance.nist.dl19-passage.json", "B": "/home/user/code/relevance_prediction/output/ranking_performance/ranking_performance.rank1-7b.dl19-passage/0.68.json"}, "metrics": {"ndcg@10": {"kendall_tau": 0.8558558558558559, "kendall_tau_p": 8.989354747556581e-14, "spearman_rho": 0.9623044096728307, "spearman_rho_p": 2.2441673781450668e-21}, "map@100": {"kendall_tau": 0.9009009009009009, "kendall_tau_p": 4.249922767583786e-15, "spearman_rho": 0.980796586059744, "spearman_rho_p": 1.943493430675664e-26}, "mrr@10": {"kendall_tau": 0.8347172188586224, "kendall_tau_p": 4.589068655265418e-13, "spearman_rho": 0.9524458955373467, "spearman_rho_p": 1.209743137794585e-19}}}, "0.23": {"n_systems": 37, "files": {"A": "/home/user/code/relevance_prediction/output/ranking_performance/ranking_performance.nist.dl19-passage.json", "B": "/home/user/code/relevance_prediction/output/ranking_performance/ranking_performance.rank1-7b.dl19-passage/0.23.json"}, "metrics": {"ndcg@10": {"kendall_tau": 0.8648648648648649, "kendall_tau_p": 4.942240688409104e-14, "spearman_rho": 0.9642010431484115, "spearman_rho_p": 9.23078457180987e-22}, "map@100": {"kendall_tau": 0.897897897897898, "kendall_tau_p": 5.233421599100931e-15, "spearman_rho": 0.9791370317686106, "spearman_rho_p": 8.182123953070416e-26}, "mrr@10": {"kendall_tau": 0.8316983500743235, "kendall_tau_p": 5.563603535575372e-13, "spearman_rho": 0.9517343627759418, "spearman_rho_p": 1.5599261236667657e-19}}}, "0.74": {"n_systems": 37, "files": {"A": "/home/user/code/relevance_prediction/output/ranking_performance/ranking_performance.nist.dl19-passage.json", "B": "/home/user/code/relevance_prediction/output/ranking_performance/ranking_performance.rank1-7b.dl19-passage/0.74.json"}, "metrics": {"ndcg@10": {"kendall_tau": 0.8558558558558559, "kendall_tau_p": 8.989354747556581e-14, "spearman_rho": 0.9623044096728307, "spearman_rho_p": 2.2441673781450668e-21}, "map@100": {"kendall_tau": 0.903903903903904, "kendall_tau_p": 3.4489238579727526e-15, "spearman_rho": 0.9810336652441916, "spearman_rho_p": 1.5666807959650767e-26}, "mrr@10": {"kendall_tau": 0.8347172188586224, "kendall_tau_p": 4.589068655265418e-13, "spearman_rho": 0.9524458955373467, "spearman_rho_p": 1.209743137794585e-19}}}, "0.45": {"n_systems": 37, "files": {"A": "/home/user/code/relevance_prediction/output/ranking_performance/ranking_performance.nist.dl19-passage.json", "B": "/home/user/code/relevance_prediction/output/ranking_performance/ranking_performance.rank1-7b.dl19-passage/0.45.json"}, "metrics": {"ndcg@10": {"kendall_tau": 0.867867867867868, "kendall_tau_p": 4.043315021590678e-14, "spearman_rho": 0.9665718349928876, "spearman_rho_p": 2.8355618337835503e-22}, "map@100": {"kendall_tau": 0.897897897897898, "kendall_tau_p": 5.233421599100931e-15, "spearman_rho": 0.9796111901375059, "spearman_rho_p": 5.492427427607869e-26}, "mrr@10": {"kendall_tau": 0.8347172188586224, "kendall_tau_p": 4.589068655265418e-13, "spearman_rho": 0.9524458955373467, "spearman_rho_p": 1.209743137794585e-19}}}, "0.85": {"n_systems": 37, "files": {"A": "/home/user/code/relevance_prediction/output/ranking_performance/ranking_performance.nist.dl19-passage.json", "B": "/home/user/code/relevance_prediction/output/ranking_performance/ranking_performance.rank1-7b.dl19-passage/0.85.json"}, "metrics": {"ndcg@10": {"kendall_tau": 0.8558558558558559, "kendall_tau_p": 8.989354747556581e-14, "spearman_rho": 0.9623044096728307, "spearman_rho_p": 2.2441673781450668e-21}, "map@100": {"kendall_tau": 0.9009009009009009, "kendall_tau_p": 4.249922767583786e-15, "spearman_rho": 0.980796586059744, "spearman_rho_p": 1.943493430675664e-26}, "mrr@10": {"kendall_tau": 0.8347172188586224, "kendall_tau_p": 4.589068655265418e-13, "spearman_rho": 0.9524458955373467, "spearman_rho_p": 1.209743137794585e-19}}}, "0.27": {"n_systems": 37, "files": {"A": "/home/user/code/relevance_prediction/output/ranking_performance/ranking_performance.nist.dl19-passage.json", "B": "/home/user/code/relevance_prediction/output/ranking_performance/ranking_performance.rank1-7b.dl19-passage/0.27.json"}, "metrics": {"ndcg@10": {"kendall_tau": 0.8648648648648649, "kendall_tau_p": 4.942240688409104e-14, "spearman_rho": 0.9646752015173067, "spearman_rho_p": 7.337277858783105e-22}, "map@100": {"kendall_tau": 0.8948948948948949, "kendall_tau_p": 6.440175279163034e-15, "spearman_rho": 0.9788999525841631, "spearman_rho_p": 9.95252340421051e-26}, "mrr@10": {"kendall_tau": 0.8316983500743235, "kendall_tau_p": 5.563603535575372e-13, "spearman_rho": 0.9517343627759418, "spearman_rho_p": 1.5599261236667657e-19}}}, "0.16": {"n_systems": 37, "files": {"A": "/home/user/code/relevance_prediction/output/ranking_performance/ranking_performance.nist.dl19-passage.json", "B": "/home/user/code/relevance_prediction/output/ranking_performance/ranking_performance.rank1-7b.dl19-passage/0.16.json"}, "metrics": {"ndcg@10": {"kendall_tau": 0.8648648648648649, "kendall_tau_p": 4.942240688409104e-14, "spearman_rho": 0.9642010431484115, "spearman_rho_p": 9.23078457180987e-22}, "map@100": {"kendall_tau": 0.897897897897898, "kendall_tau_p": 5.233421599100931e-15, "spearman_rho": 0.9791370317686106, "spearman_rho_p": 8.182123953070416e-26}, "mrr@10": {"kendall_tau": 0.8316983500743235, "kendall_tau_p": 5.563603535575372e-13, "spearman_rho": 0.9517343627759418, "spearman_rho_p": 1.5599261236667657e-19}}}, "0.0": {"n_systems": 37, "files": {"A": "/home/user/code/relevance_prediction/output/ranking_performance/ranking_performance.nist.dl19-passage.json", "B": "/home/user/code/relevance_prediction/output/ranking_performance/ranking_performance.rank1-7b.dl19-passage/0.0.json"}, "metrics": {"ndcg@10": {"kendall_tau": -0.08774713684868254, "kendall_tau_p": 0.5196421135179725, "spearman_rho": -0.11080523589708723, "spearman_rho_p": 0.5138313059165325}, "map@100": {"kendall_tau": 0.2222222222222222, "kendall_tau_p": 0.05290758985102452, "spearman_rho": 0.31057373162636315, "spearman_rho_p": 0.06136332269158208}, "mrr@10": {"kendall_tau": NaN, "kendall_tau_p": NaN, "spearman_rho": NaN, "spearman_rho_p": NaN}}}, "0.51": {"n_systems": 37, "files": {"A": "/home/user/code/relevance_prediction/output/ranking_performance/ranking_performance.nist.dl19-passage.json", "B": "/home/user/code/relevance_prediction/output/ranking_performance/ranking_performance.rank1-7b.dl19-passage/0.51.json"}, "metrics": {"ndcg@10": {"kendall_tau": 0.8528528528528528, "kendall_tau_p": 1.0958355703875995e-13, "spearman_rho": 0.9615931721194878, "spearman_rho_p": 3.095035855301447e-21}, "map@100": {"kendall_tau": 0.897897897897898, "kendall_tau_p": 5.233421599100931e-15, "spearman_rho": 0.9803224276908485, "spearman_rho_p": 2.9671574948533413e-26}, "mrr@10": {"kendall_tau": 0.8347172188586224, "kendall_tau_p": 4.589068655265418e-13, "spearman_rho": 0.9524458955373467, "spearman_rho_p": 1.209743137794585e-19}}}, "0.89": {"n_systems": 37, "files": {"A": "/home/user/code/relevance_prediction/output/ranking_performance/ranking_performance.nist.dl19-passage.json", "B": "/home/user/code/relevance_prediction/output/ranking_performance/ranking_performance.rank1-7b.dl19-passage/0.89.json"}, "metrics": {"ndcg@10": {"kendall_tau": 0.8498498498498499, "kendall_tau_p": 1.3349653228005416e-13, "spearman_rho": 0.9611190137505926, "spearman_rho_p": 3.8219476497508666e-21}, "map@100": {"kendall_tau": 0.9009009009009009, "kendall_tau_p": 4.249922767583786e-15, "spearman_rho": 0.980796586059744, "spearman_rho_p": 1.943493430675664e-26}, "mrr@10": {"kendall_tau": 0.8347172188586224, "kendall_tau_p": 4.589068655265418e-13, "spearman_rho": 0.9524458955373467, "spearman_rho_p": 1.209743137794585e-19}}}, "0.49": {"n_systems": 37, "files": {"A": "/home/user/code/relevance_prediction/output/ranking_performance/ranking_performance.nist.dl19-passage.json", "B": "/home/user/code/relevance_prediction/output/ranking_performance/ranking_performance.rank1-7b.dl19-passage/0.49.json"}, "metrics": {"ndcg@10": {"kendall_tau": 0.8528528528528528, "kendall_tau_p": 1.0958355703875995e-13, "spearman_rho": 0.9615931721194878, "spearman_rho_p": 3.095035855301447e-21}, "map@100": {"kendall_tau": 0.9009009009009009, "kendall_tau_p": 4.249922767583786e-15, "spearman_rho": 0.9805595068752962, "spearman_rho_p": 2.4045126982738695e-26}, "mrr@10": {"kendall_tau": 0.8347172188586224, "kendall_tau_p": 4.589068655265418e-13, "spearman_rho": 0.9524458955373467, "spearman_rho_p": 1.209743137794585e-19}}}, "0.02": {"n_systems": 37, "files": {"A": "/home/user/code/relevance_prediction/output/ranking_performance/ranking_performance.nist.dl19-passage.json", "B": "/home/user/code/relevance_prediction/output/ranking_performance/ranking_performance.rank1-7b.dl19-passage/0.02.json"}, "metrics": {"ndcg@10": {"kendall_tau": 0.8858858858858859, "kendall_tau_p": 1.1953017059610019e-14, "spearman_rho": 0.9743954480796585, "spearman_rho_p": 2.838535646228554e-24}, "map@100": {"kendall_tau": 0.9009009009009009, "kendall_tau_p": 4.249922767583786e-15, "spearman_rho": 0.9803224276908485, "spearman_rho_p": 2.9671574948533413e-26}, "mrr@10": {"kendall_tau": 0.84075495642722, "kendall_tau_p": 3.1159042035603546e-13, "spearman_rho": 0.9543433162344267, "spearman_rho_p": 6.022796807655077e-20}}}, "0.33": {"n_systems": 37, "files": {"A": "/home/user/code/relevance_prediction/output/ranking_performance/ranking_performance.nist.dl19-passage.json", "B": "/home/user/code/relevance_prediction/output/ranking_performance/ranking_performance.rank1-7b.dl19-passage/0.33.json"}, "metrics": {"ndcg@10": {"kendall_tau": 0.867867867867868, "kendall_tau_p": 4.043315021590678e-14, "spearman_rho": 0.9665718349928876, "spearman_rho_p": 2.8355618337835503e-22}, "map@100": {"kendall_tau": 0.897897897897898, "kendall_tau_p": 5.233421599100931e-15, "spearman_rho": 0.9796111901375059, "spearman_rho_p": 5.492427427607869e-26}, "mrr@10": {"kendall_tau": 0.8347172188586224, "kendall_tau_p": 4.589068655265418e-13, "spearman_rho": 0.9524458955373467, "spearman_rho_p": 1.209743137794585e-19}}}, "0.78": {"n_systems": 37, "files": {"A": "/home/user/code/relevance_prediction/output/ranking_performance/ranking_performance.nist.dl19-passage.json", "B": "/home/user/code/relevance_prediction/output/ranking_performance/ranking_performance.rank1-7b.dl19-passage/0.78.json"}, "metrics": {"ndcg@10": {"kendall_tau": 0.8558558558558559, "kendall_tau_p": 8.989354747556581e-14, "spearman_rho": 0.9623044096728307, "spearman_rho_p": 2.2441673781450668e-21}, "map@100": {"kendall_tau": 0.9009009009009009, "kendall_tau_p": 4.249922767583786e-15, "spearman_rho": 0.980796586059744, "spearman_rho_p": 1.943493430675664e-26}, "mrr@10": {"kendall_tau": 0.8347172188586224, "kendall_tau_p": 4.589068655265418e-13, "spearman_rho": 0.9524458955373467, "spearman_rho_p": 1.209743137794585e-19}}}, "0.91": {"n_systems": 37, "files": {"A": "/home/user/code/relevance_prediction/output/ranking_performance/ranking_performance.nist.dl19-passage.json", "B": "/home/user/code/relevance_prediction/output/ranking_performance/ranking_performance.rank1-7b.dl19-passage/0.91.json"}, "metrics": {"ndcg@10": {"kendall_tau": 0.8498498498498499, "kendall_tau_p": 1.3349653228005416e-13, "spearman_rho": 0.9611190137505926, "spearman_rho_p": 3.8219476497508666e-21}, "map@100": {"kendall_tau": 0.903903903903904, "kendall_tau_p": 3.4489238579727526e-15, "spearman_rho": 0.980796586059744, "spearman_rho_p": 1.943493430675664e-26}, "mrr@10": {"kendall_tau": 0.8347172188586224, "kendall_tau_p": 4.589068655265418e-13, "spearman_rho": 0.9524458955373467, "spearman_rho_p": 1.209743137794585e-19}}}, "0.64": {"n_systems": 37, "files": {"A": "/home/user/code/relevance_prediction/output/ranking_performance/ranking_performance.nist.dl19-passage.json", "B": "/home/user/code/relevance_prediction/output/ranking_performance/ranking_performance.rank1-7b.dl19-passage/0.64.json"}, "metrics": {"ndcg@10": {"kendall_tau": 0.8558558558558559, "kendall_tau_p": 8.989354747556581e-14, "spearman_rho": 0.9623044096728307, "spearman_rho_p": 2.2441673781450668e-21}, "map@100": {"kendall_tau": 0.9009009009009009, "kendall_tau_p": 4.249922767583786e-15, "spearman_rho": 0.980796586059744, "spearman_rho_p": 1.943493430675664e-26}, "mrr@10": {"kendall_tau": 0.8347172188586224, "kendall_tau_p": 4.589068655265418e-13, "spearman_rho": 0.9524458955373467, "spearman_rho_p": 1.209743137794585e-19}}}, "0.8": {"n_systems": 37, "files": {"A": "/home/user/code/relevance_prediction/output/ranking_performance/ranking_performance.nist.dl19-passage.json", "B": "/home/user/code/relevance_prediction/output/ranking_performance/ranking_performance.rank1-7b.dl19-passage/0.8.json"}, "metrics": {"ndcg@10": {"kendall_tau": 0.8558558558558559, "kendall_tau_p": 8.989354747556581e-14, "spearman_rho": 0.9623044096728307, "spearman_rho_p": 2.2441673781450668e-21}, "map@100": {"kendall_tau": 0.9009009009009009, "kendall_tau_p": 4.249922767583786e-15, "spearman_rho": 0.980796586059744, "spearman_rho_p": 1.943493430675664e-26}, "mrr@10": {"kendall_tau": 0.8347172188586224, "kendall_tau_p": 4.589068655265418e-13, "spearman_rho": 0.9524458955373467, "spearman_rho_p": 1.209743137794585e-19}}}, "0.55": {"n_systems": 37, "files": {"A": "/home/user/code/relevance_prediction/output/ranking_performance/ranking_performance.nist.dl19-passage.json", "B": "/home/user/code/relevance_prediction/output/ranking_performance/ranking_performance.rank1-7b.dl19-passage/0.55.json"}, "metrics": {"ndcg@10": {"kendall_tau": 0.8468468468468467, "kendall_tau_p": 1.625183200282792e-13, "spearman_rho": 0.9601706970128023, "spearman_rho_p": 5.783059808490516e-21}, "map@100": {"kendall_tau": 0.897897897897898, "kendall_tau_p": 5.233421599100931e-15, "spearman_rho": 0.9803224276908485, "spearman_rho_p": 2.9671574948533413e-26}, "mrr@10": {"kendall_tau": 0.8347172188586224, "kendall_tau_p": 4.589068655265418e-13, "spearman_rho": 0.9524458955373467, "spearman_rho_p": 1.209743137794585e-19}}}, "0.37": {"n_systems": 37, "files": {"A": "/home/user/code/relevance_prediction/output/ranking_performance/ranking_performance.nist.dl19-passage.json", "B": "/home/user/code/relevance_prediction/output/ranking_performance/ranking_performance.rank1-7b.dl19-passage/0.37.json"}, "metrics": {"ndcg@10": {"kendall_tau": 0.867867867867868, "kendall_tau_p": 4.043315021590678e-14, "spearman_rho": 0.9665718349928876, "spearman_rho_p": 2.8355618337835503e-22}, "map@100": {"kendall_tau": 0.897897897897898, "kendall_tau_p": 5.233421599100931e-15, "spearman_rho": 0.9796111901375059, "spearman_rho_p": 5.492427427607869e-26}, "mrr@10": {"kendall_tau": 0.8347172188586224, "kendall_tau_p": 4.589068655265418e-13, "spearman_rho": 0.9524458955373467, "spearman_rho_p": 1.209743137794585e-19}}}, "0.95": {"n_systems": 37, "files": {"A": "/home/user/code/relevance_prediction/output/ranking_performance/ranking_performance.nist.dl19-passage.json", "B": "/home/user/code/relevance_prediction/output/ranking_performance/ranking_performance.rank1-7b.dl19-passage/0.95.json"}, "metrics": {"ndcg@10": {"kendall_tau": 0.8528528528528528, "kendall_tau_p": 1.0958355703875995e-13, "spearman_rho": 0.9615931721194878, "spearman_rho_p": 3.095035855301447e-21}, "map@100": {"kendall_tau": 0.9069069069069069, "kendall_tau_p": 2.7970060241623902e-15, "spearman_rho": 0.9819819819819817, "spearman_rho_p": 6.432573289308798e-27}, "mrr@10": {"kendall_tau": 0.8347172188586224, "kendall_tau_p": 4.589068655265418e-13, "spearman_rho": 0.9524458955373467, "spearman_rho_p": 1.209743137794585e-19}}}, "0.06": {"n_systems": 37, "files": {"A": "/home/user/code/relevance_prediction/output/ranking_performance/ranking_performance.nist.dl19-passage.json", "B": "/home/user/code/relevance_prediction/output/ranking_performance/ranking_performance.rank1-7b.dl19-passage/0.06.json"}, "metrics": {"ndcg@10": {"kendall_tau": 0.8648648648648649, "kendall_tau_p": 4.942240688409104e-14, "spearman_rho": 0.9670459933617828, "spearman_rho_p": 2.21663974549793e-22}, "map@100": {"kendall_tau": 0.9069069069069069, "kendall_tau_p": 2.7970060241623902e-15, "spearman_rho": 0.9810336652441916, "spearman_rho_p": 1.5666807959650767e-26}, "mrr@10": {"kendall_tau": 0.8316983500743235, "kendall_tau_p": 5.563603535575372e-13, "spearman_rho": 0.9512600076016718, "spearman_rho_p": 1.8441240005327494e-19}}}, "0.88": {"n_systems": 37, "files": {"A": "/home/user/code/relevance_prediction/output/ranking_performance/ranking_performance.nist.dl19-passage.json", "B": "/home/user/code/relevance_prediction/output/ranking_performance/ranking_performance.rank1-7b.dl19-passage/0.88.json"}, "metrics": {"ndcg@10": {"kendall_tau": 0.8528528528528528, "kendall_tau_p": 1.0958355703875995e-13, "spearman_rho": 0.9615931721194878, "spearman_rho_p": 3.095035855301447e-21}, "map@100": {"kendall_tau": 0.9009009009009009, "kendall_tau_p": 4.249922767583786e-15, "spearman_rho": 0.980796586059744, "spearman_rho_p": 1.943493430675664e-26}, "mrr@10": {"kendall_tau": 0.8347172188586224, "kendall_tau_p": 4.589068655265418e-13, "spearman_rho": 0.9524458955373467, "spearman_rho_p": 1.209743137794585e-19}}}, "0.61": {"n_systems": 37, "files": {"A": "/home/user/code/relevance_prediction/output/ranking_performance/ranking_performance.nist.dl19-passage.json", "B": "/home/user/code/relevance_prediction/output/ranking_performance/ranking_performance.rank1-7b.dl19-passage/0.61.json"}, "metrics": {"ndcg@10": {"kendall_tau": 0.8558558558558559, "kendall_tau_p": 8.989354747556581e-14, "spearman_rho": 0.9623044096728307, "spearman_rho_p": 2.2441673781450668e-21}, "map@100": {"kendall_tau": 0.9009009009009009, "kendall_tau_p": 4.249922767583786e-15, "spearman_rho": 0.980796586059744, "spearman_rho_p": 1.943493430675664e-26}, "mrr@10": {"kendall_tau": 0.8347172188586224, "kendall_tau_p": 4.589068655265418e-13, "spearman_rho": 0.9524458955373467, "spearman_rho_p": 1.209743137794585e-19}}}, "0.03": {"n_systems": 37, "files": {"A": "/home/user/code/relevance_prediction/output/ranking_performance/ranking_performance.nist.dl19-passage.json", "B": "/home/user/code/relevance_prediction/output/ranking_performance/ranking_performance.rank1-7b.dl19-passage/0.03.json"}, "metrics": {"ndcg@10": {"kendall_tau": 0.8798798798798799, "kendall_tau_p": 1.7991512842727367e-14, "spearman_rho": 0.974158368895211, "spearman_rho_p": 3.329119549716439e-24}, "map@100": {"kendall_tau": 0.9069069069069069, "kendall_tau_p": 2.7970060241623902e-15, "spearman_rho": 0.9817449027975342, "spearman_rho_p": 8.070945542860349e-27}, "mrr@10": {"kendall_tau": 0.84075495642722, "kendall_tau_p": 3.1159042035603546e-13, "spearman_rho": 0.9543433162344267, "spearman_rho_p": 6.022796807655077e-20}}}, "0.48": {"n_systems": 37, "files": {"A": "/home/user/code/relevance_prediction/output/ranking_performance/ranking_performance.nist.dl19-passage.json", "B": "/home/user/code/relevance_prediction/output/ranking_performance/ranking_performance.rank1-7b.dl19-passage/0.48.json"}, "metrics": {"ndcg@10": {"kendall_tau": 0.867867867867868, "kendall_tau_p": 4.043315021590678e-14, "spearman_rho": 0.9665718349928876, "spearman_rho_p": 2.8355618337835503e-22}, "map@100": {"kendall_tau": 0.897897897897898, "kendall_tau_p": 5.233421599100931e-15, "spearman_rho": 0.9796111901375059, "spearman_rho_p": 5.492427427607869e-26}, "mrr@10": {"kendall_tau": 0.8347172188586224, "kendall_tau_p": 4.589068655265418e-13, "spearman_rho": 0.9524458955373467, "spearman_rho_p": 1.209743137794585e-19}}}, "0.79": {"n_systems": 37, "files": {"A": "/home/user/code/relevance_prediction/output/ranking_performance/ranking_performance.nist.dl19-passage.json", "B": "/home/user/code/relevance_prediction/output/ranking_performance/ranking_performance.rank1-7b.dl19-passage/0.79.json"}, "metrics": {"ndcg@10": {"kendall_tau": 0.8558558558558559, "kendall_tau_p": 8.989354747556581e-14, "spearman_rho": 0.9623044096728307, "spearman_rho_p": 2.2441673781450668e-21}, "map@100": {"kendall_tau": 0.9009009009009009, "kendall_tau_p": 4.249922767583786e-15, "spearman_rho": 0.980796586059744, "spearman_rho_p": 1.943493430675664e-26}, "mrr@10": {"kendall_tau": 0.8347172188586224, "kendall_tau_p": 4.589068655265418e-13, "spearman_rho": 0.9524458955373467, "spearman_rho_p": 1.209743137794585e-19}}}, "0.32": {"n_systems": 37, "files": {"A": "/home/user/code/relevance_prediction/output/ranking_performance/ranking_performance.nist.dl19-passage.json", "B": "/home/user/code/relevance_prediction/output/ranking_performance/ranking_performance.rank1-7b.dl19-passage/0.32.json"}, "metrics": {"ndcg@10": {"kendall_tau": 0.8738738738738738, "kendall_tau_p": 2.700770114420909e-14, "spearman_rho": 0.9684684684684685, "spearman_rho_p": 1.0356955031590111e-22}, "map@100": {"kendall_tau": 0.9009009009009009, "kendall_tau_p": 4.249922767583786e-15, "spearman_rho": 0.9810336652441916, "spearman_rho_p": 1.5666807959650767e-26}, "mrr@10": {"kendall_tau": 0.8347172188586224, "kendall_tau_p": 4.589068655265418e-13, "spearman_rho": 0.9524458955373467, "spearman_rho_p": 1.209743137794585e-19}}}, "0.65": {"n_systems": 37, "files": {"A": "/home/user/code/relevance_prediction/output/ranking_performance/ranking_performance.nist.dl19-passage.json", "B": "/home/user/code/relevance_prediction/output/ranking_performance/ranking_performance.rank1-7b.dl19-passage/0.65.json"}, "metrics": {"ndcg@10": {"kendall_tau": 0.8558558558558559, "kendall_tau_p": 8.989354747556581e-14, "spearman_rho": 0.9623044096728307, "spearman_rho_p": 2.2441673781450668e-21}, "map@100": {"kendall_tau": 0.9009009009009009, "kendall_tau_p": 4.249922767583786e-15, "spearman_rho": 0.980796586059744, "spearman_rho_p": 1.943493430675664e-26}, "mrr@10": {"kendall_tau": 0.8347172188586224, "kendall_tau_p": 4.589068655265418e-13, "spearman_rho": 0.9524458955373467, "spearman_rho_p": 1.209743137794585e-19}}}, "0.54": {"n_systems": 37, "files": {"A": "/home/user/code/relevance_prediction/output/ranking_performance/ranking_performance.nist.dl19-passage.json", "B": "/home/user/code/relevance_prediction/output/ranking_performance/ranking_performance.rank1-7b.dl19-passage/0.54.json"}, "metrics": {"ndcg@10": {"kendall_tau": 0.8468468468468467, "kendall_tau_p": 1.625183200282792e-13, "spearman_rho": 0.9601706970128023, "spearman_rho_p": 5.783059808490516e-21}, "map@100": {"kendall_tau": 0.897897897897898, "kendall_tau_p": 5.233421599100931e-15, "spearman_rho": 0.9803224276908485, "spearman_rho_p": 2.9671574948533413e-26}, "mrr@10": {"kendall_tau": 0.8347172188586224, "kendall_tau_p": 4.589068655265418e-13, "spearman_rho": 0.9524458955373467, "spearman_rho_p": 1.209743137794585e-19}}}, "0.9": {"n_systems": 37, "files": {"A": "/home/user/code/relevance_prediction/output/ranking_performance/ranking_performance.nist.dl19-passage.json", "B": "/home/user/code/relevance_prediction/output/ranking_performance/ranking_performance.rank1-7b.dl19-passage/0.9.json"}, "metrics": {"ndcg@10": {"kendall_tau": 0.8498498498498499, "kendall_tau_p": 1.3349653228005416e-13, "spearman_rho": 0.9611190137505926, "spearman_rho_p": 3.8219476497508666e-21}, "map@100": {"kendall_tau": 0.9009009009009009, "kendall_tau_p": 4.249922767583786e-15, "spearman_rho": 0.980796586059744, "spearman_rho_p": 1.943493430675664e-26}, "mrr@10": {"kendall_tau": 0.8347172188586224, "kendall_tau_p": 4.589068655265418e-13, "spearman_rho": 0.9524458955373467, "spearman_rho_p": 1.209743137794585e-19}}}, "0.36": {"n_systems": 37, "files": {"A": "/home/user/code/relevance_prediction/output/ranking_performance/ranking_performance.nist.dl19-passage.json", "B": "/home/user/code/relevance_prediction/output/ranking_performance/ranking_performance.rank1-7b.dl19-passage/0.36.json"}, "metrics": {"ndcg@10": {"kendall_tau": 0.867867867867868, "kendall_tau_p": 4.043315021590678e-14, "spearman_rho": 0.9665718349928876, "spearman_rho_p": 2.8355618337835503e-22}, "map@100": {"kendall_tau": 0.897897897897898, "kendall_tau_p": 5.233421599100931e-15, "spearman_rho": 0.9796111901375059, "spearman_rho_p": 5.492427427607869e-26}, "mrr@10": {"kendall_tau": 0.8347172188586224, "kendall_tau_p": 4.589068655265418e-13, "spearman_rho": 0.9524458955373467, "spearman_rho_p": 1.209743137794585e-19}}}, "0.94": {"n_systems": 37, "files": {"A": "/home/user/code/relevance_prediction/output/ranking_performance/ranking_performance.nist.dl19-passage.json", "B": "/home/user/code/relevance_prediction/output/ranking_performance/ranking_performance.rank1-7b.dl19-passage/0.94.json"}, "metrics": {"ndcg@10": {"kendall_tau": 0.8498498498498499, "kendall_tau_p": 1.3349653228005416e-13, "spearman_rho": 0.9611190137505926, "spearman_rho_p": 3.8219476497508666e-21}, "map@100": {"kendall_tau": 0.9009009009009009, "kendall_tau_p": 4.249922767583786e-15, "spearman_rho": 0.980796586059744, "spearman_rho_p": 1.943493430675664e-26}, "mrr@10": {"kendall_tau": 0.8347172188586224, "kendall_tau_p": 4.589068655265418e-13, "spearman_rho": 0.9524458955373467, "spearman_rho_p": 1.209743137794585e-19}}}, "0.07": {"n_systems": 37, "files": {"A": "/home/user/code/relevance_prediction/output/ranking_performance/ranking_performance.nist.dl19-passage.json", "B": "/home/user/code/relevance_prediction/output/ranking_performance/ranking_performance.rank1-7b.dl19-passage/0.07.json"}, "metrics": {"ndcg@10": {"kendall_tau": 0.8588588588588588, "kendall_tau_p": 7.369182830354849e-14, "spearman_rho": 0.9653864390706496, "spearman_rho_p": 5.168915433401108e-22}, "map@100": {"kendall_tau": 0.9069069069069069, "kendall_tau_p": 2.7970060241623902e-15, "spearman_rho": 0.9810336652441916, "spearman_rho_p": 1.5666807959650767e-26}, "mrr@10": {"kendall_tau": 0.8316983500743235, "kendall_tau_p": 5.563603535575372e-13, "spearman_rho": 0.9512600076016718, "spearman_rho_p": 1.8441240005327494e-19}}}, "0.71": {"n_systems": 37, "files": {"A": "/home/user/code/relevance_prediction/output/ranking_performance/ranking_performance.nist.dl19-passage.json", "B": "/home/user/code/relevance_prediction/output/ranking_performance/ranking_performance.rank1-7b.dl19-passage/0.71.json"}, "metrics": {"ndcg@10": {"kendall_tau": 0.8558558558558559, "kendall_tau_p": 8.989354747556581e-14, "spearman_rho": 0.9623044096728307, "spearman_rho_p": 2.2441673781450668e-21}, "map@100": {"kendall_tau": 0.903903903903904, "kendall_tau_p": 3.4489238579727526e-15, "spearman_rho": 0.9810336652441916, "spearman_rho_p": 1.5666807959650767e-26}, "mrr@10": {"kendall_tau": 0.8347172188586224, "kendall_tau_p": 4.589068655265418e-13, "spearman_rho": 0.9524458955373467, "spearman_rho_p": 1.209743137794585e-19}}}, "0.98": {"n_systems": 37, "files": {"A": "/home/user/code/relevance_prediction/output/ranking_performance/ranking_performance.nist.dl19-passage.json", "B": "/home/user/code/relevance_prediction/output/ranking_performance/ranking_performance.rank1-7b.dl19-passage/0.98.json"}, "metrics": {"ndcg@10": {"kendall_tau": 0.8528528528528528, "kendall_tau_p": 1.0958355703875995e-13, "spearman_rho": 0.9627785680417258, "spearman_rho_p": 1.805028800574076e-21}, "map@100": {"kendall_tau": 0.9069069069069069, "kendall_tau_p": 2.7970060241623902e-15, "spearman_rho": 0.9819819819819817, "spearman_rho_p": 6.432573289308798e-27}, "mrr@10": {"kendall_tau": 0.8347172188586224, "kendall_tau_p": 4.589068655265418e-13, "spearman_rho": 0.9524458955373467, "spearman_rho_p": 1.209743137794585e-19}}}, "0.5": {"n_systems": 37, "files": {"A": "/home/user/code/relevance_prediction/output/ranking_performance/ranking_performance.nist.dl19-passage.json", "B": "/home/user/code/relevance_prediction/output/ranking_performance/ranking_performance.rank1-7b.dl19-passage/0.5.json"}, "metrics": {"ndcg@10": {"kendall_tau": 0.8528528528528528, "kendall_tau_p": 1.0958355703875995e-13, "spearman_rho": 0.9615931721194878, "spearman_rho_p": 3.095035855301447e-21}, "map@100": {"kendall_tau": 0.9009009009009009, "kendall_tau_p": 4.249922767583786e-15, "spearman_rho": 0.9805595068752962, "spearman_rho_p": 2.4045126982738695e-26}, "mrr@10": {"kendall_tau": 0.8347172188586224, "kendall_tau_p": 4.589068655265418e-13, "spearman_rho": 0.9524458955373467, "spearman_rho_p": 1.209743137794585e-19}}}, "0.58": {"n_systems": 37, "files": {"A": "/home/user/code/relevance_prediction/output/ranking_performance/ranking_performance.nist.dl19-passage.json", "B": "/home/user/code/relevance_prediction/output/ranking_performance/ranking_performance.rank1-7b.dl19-passage/0.58.json"}, "metrics": {"ndcg@10": {"kendall_tau": 0.8468468468468467, "kendall_tau_p": 1.625183200282792e-13, "spearman_rho": 0.9601706970128023, "spearman_rho_p": 5.783059808490516e-21}, "map@100": {"kendall_tau": 0.897897897897898, "kendall_tau_p": 5.233421599100931e-15, "spearman_rho": 0.9803224276908485, "spearman_rho_p": 2.9671574948533413e-26}, "mrr@10": {"kendall_tau": 0.8347172188586224, "kendall_tau_p": 4.589068655265418e-13, "spearman_rho": 0.9524458955373467, "spearman_rho_p": 1.209743137794585e-19}}}, "0.13": {"n_systems": 37, "files": {"A": "/home/user/code/relevance_prediction/output/ranking_performance/ranking_performance.nist.dl19-passage.json", "B": "/home/user/code/relevance_prediction/output/ranking_performance/ranking_performance.rank1-7b.dl19-passage/0.13.json"}, "metrics": {"ndcg@10": {"kendall_tau": 0.8618618618618619, "kendall_tau_p": 6.036953062344684e-14, "spearman_rho": 0.9642010431484115, "spearman_rho_p": 9.23078457180987e-22}, "map@100": {"kendall_tau": 0.9009009009009009, "kendall_tau_p": 4.249922767583786e-15, "spearman_rho": 0.9798482693219533, "spearman_rho_p": 4.48418548500829e-26}, "mrr@10": {"kendall_tau": 0.8316983500743235, "kendall_tau_p": 5.563603535575372e-13, "spearman_rho": 0.9512600076016718, "spearman_rho_p": 1.8441240005327494e-19}}}, "0.22": {"n_systems": 37, "files": {"A": "/home/user/code/relevance_prediction/output/ranking_performance/ranking_performance.nist.dl19-passage.json", "B": "/home/user/code/relevance_prediction/output/ranking_performance/ranking_performance.rank1-7b.dl19-passage/0.22.json"}, "metrics": {"ndcg@10": {"kendall_tau": 0.8648648648648649, "kendall_tau_p": 4.942240688409104e-14, "spearman_rho": 0.9642010431484115, "spearman_rho_p": 9.23078457180987e-22}, "map@100": {"kendall_tau": 0.897897897897898, "kendall_tau_p": 5.233421599100931e-15, "spearman_rho": 0.9791370317686106, "spearman_rho_p": 8.182123953070416e-26}, "mrr@10": {"kendall_tau": 0.8316983500743235, "kendall_tau_p": 5.563603535575372e-13, "spearman_rho": 0.9517343627759418, "spearman_rho_p": 1.5599261236667657e-19}}}, "0.69": {"n_systems": 37, "files": {"A": "/home/user/code/relevance_prediction/output/ranking_performance/ranking_performance.nist.dl19-passage.json", "B": "/home/user/code/relevance_prediction/output/ranking_performance/ranking_performance.rank1-7b.dl19-passage/0.69.json"}, "metrics": {"ndcg@10": {"kendall_tau": 0.8558558558558559, "kendall_tau_p": 8.989354747556581e-14, "spearman_rho": 0.9623044096728307, "spearman_rho_p": 2.2441673781450668e-21}, "map@100": {"kendall_tau": 0.903903903903904, "kendall_tau_p": 3.4489238579727526e-15, "spearman_rho": 0.9810336652441916, "spearman_rho_p": 1.5666807959650767e-26}, "mrr@10": {"kendall_tau": 0.8347172188586224, "kendall_tau_p": 4.589068655265418e-13, "spearman_rho": 0.9524458955373467, "spearman_rho_p": 1.209743137794585e-19}}}, "0.75": {"n_systems": 37, "files": {"A": "/home/user/code/relevance_prediction/output/ranking_performance/ranking_performance.nist.dl19-passage.json", "B": "/home/user/code/relevance_prediction/output/ranking_performance/ranking_performance.rank1-7b.dl19-passage/0.75.json"}, "metrics": {"ndcg@10": {"kendall_tau": 0.8558558558558559, "kendall_tau_p": 8.989354747556581e-14, "spearman_rho": 0.9623044096728307, "spearman_rho_p": 2.2441673781450668e-21}, "map@100": {"kendall_tau": 0.903903903903904, "kendall_tau_p": 3.4489238579727526e-15, "spearman_rho": 0.9810336652441916, "spearman_rho_p": 1.5666807959650767e-26}, "mrr@10": {"kendall_tau": 0.8347172188586224, "kendall_tau_p": 4.589068655265418e-13, "spearman_rho": 0.9524458955373467, "spearman_rho_p": 1.209743137794585e-19}}}, "0.44": {"n_systems": 37, "files": {"A": "/home/user/code/relevance_prediction/output/ranking_performance/ranking_performance.nist.dl19-passage.json", "B": "/home/user/code/relevance_prediction/output/ranking_performance/ranking_performance.rank1-7b.dl19-passage/0.44.json"}, "metrics": {"ndcg@10": {"kendall_tau": 0.867867867867868, "kendall_tau_p": 4.043315021590678e-14, "spearman_rho": 0.9665718349928876, "spearman_rho_p": 2.8355618337835503e-22}, "map@100": {"kendall_tau": 0.897897897897898, "kendall_tau_p": 5.233421599100931e-15, "spearman_rho": 0.9796111901375059, "spearman_rho_p": 5.492427427607869e-26}, "mrr@10": {"kendall_tau": 0.8347172188586224, "kendall_tau_p": 4.589068655265418e-13, "spearman_rho": 0.9524458955373467, "spearman_rho_p": 1.209743137794585e-19}}}, "0.84": {"n_systems": 37, "files": {"A": "/home/user/code/relevance_prediction/output/ranking_performance/ranking_performance.nist.dl19-passage.json", "B": "/home/user/code/relevance_prediction/output/ranking_performance/ranking_performance.rank1-7b.dl19-passage/0.84.json"}, "metrics": {"ndcg@10": {"kendall_tau": 0.8558558558558559, "kendall_tau_p": 8.989354747556581e-14, "spearman_rho": 0.9623044096728307, "spearman_rho_p": 2.2441673781450668e-21}, "map@100": {"kendall_tau": 0.9009009009009009, "kendall_tau_p": 4.249922767583786e-15, "spearman_rho": 0.980796586059744, "spearman_rho_p": 1.943493430675664e-26}, "mrr@10": {"kendall_tau": 0.8347172188586224, "kendall_tau_p": 4.589068655265418e-13, "spearman_rho": 0.9524458955373467, "spearman_rho_p": 1.209743137794585e-19}}}, "0.26": {"n_systems": 37, "files": {"A": "/home/user/code/relevance_prediction/output/ranking_performance/ranking_performance.nist.dl19-passage.json", "B": "/home/user/code/relevance_prediction/output/ranking_performance/ranking_performance.rank1-7b.dl19-passage/0.26.json"}, "metrics": {"ndcg@10": {"kendall_tau": 0.8648648648648649, "kendall_tau_p": 4.942240688409104e-14, "spearman_rho": 0.9646752015173067, "spearman_rho_p": 7.337277858783105e-22}, "map@100": {"kendall_tau": 0.8948948948948949, "kendall_tau_p": 6.440175279163034e-15, "spearman_rho": 0.9788999525841631, "spearman_rho_p": 9.95252340421051e-26}, "mrr@10": {"kendall_tau": 0.8316983500743235, "kendall_tau_p": 5.563603535575372e-13, "spearman_rho": 0.9517343627759418, "spearman_rho_p": 1.5599261236667657e-19}}}, "0.1": {"n_systems": 37, "files": {"A": "/home/user/code/relevance_prediction/output/ranking_performance/ranking_performance.nist.dl19-passage.json", "B": "/home/user/code/relevance_prediction/output/ranking_performance/ranking_performance.rank1-7b.dl19-passage/0.1.json"}, "metrics": {"ndcg@10": {"kendall_tau": 0.8468468468468467, "kendall_tau_p": 1.625183200282792e-13, "spearman_rho": 0.9604077761972498, "spearman_rho_p": 5.219172690474418e-21}, "map@100": {"kendall_tau": 0.9009009009009009, "kendall_tau_p": 4.249922767583786e-15, "spearman_rho": 0.9803224276908485, "spearman_rho_p": 2.9671574948533413e-26}, "mrr@10": {"kendall_tau": 0.8316983500743235, "kendall_tau_p": 5.563603535575372e-13, "spearman_rho": 0.9512600076016718, "spearman_rho_p": 1.8441240005327494e-19}}}, "0.17": {"n_systems": 37, "files": {"A": "/home/user/code/relevance_prediction/output/ranking_performance/ranking_performance.nist.dl19-passage.json", "B": "/home/user/code/relevance_prediction/output/ranking_performance/ranking_performance.rank1-7b.dl19-passage/0.17.json"}, "metrics": {"ndcg@10": {"kendall_tau": 0.8648648648648649, "kendall_tau_p": 4.942240688409104e-14, "spearman_rho": 0.9642010431484115, "spearman_rho_p": 9.23078457180987e-22}, "map@100": {"kendall_tau": 0.897897897897898, "kendall_tau_p": 5.233421599100931e-15, "spearman_rho": 0.9791370317686106, "spearman_rho_p": 8.182123953070416e-26}, "mrr@10": {"kendall_tau": 0.8316983500743235, "kendall_tau_p": 5.563603535575372e-13, "spearman_rho": 0.9517343627759418, "spearman_rho_p": 1.5599261236667657e-19}}}}